LICENSE
MANIFEST.in
README.rst
ez_setup.py
setup.cfg
setup.py
doc/Makefile
doc/conf.py
doc/index.rst
doc/make.bat
pydons/__init__.py
pydons/hdf5util.py
pydons.egg-info/PKG-INFO
pydons.egg-info/SOURCES.txt
pydons.egg-info/dependency_links.txt
pydons.egg-info/requires.txt
pydons.egg-info/top_level.txt
tests/test_attrs.py
tests/test_basic.py
tests/test_diff.py
tests/test_file_browser.py
tests/test_file_browser_netcdf4.py
tests/test_storage.py