Metadata-Version: 1.1
Name: pydons
Version: 0.2.5
Summary: Python data manimulation add-ons
Home-page: https://bitbucket.org/urbanj/pydons
Author: Jakub Urban
Author-email: coobas at gmail dt com
License: MIT
Keywords: hdf5 netCDF matlab
Platform: UNKNOWN
Classifier: Programming Language :: Python :: 2.6
Classifier: Programming Language :: Python :: 2.7
Classifier: Programming Language :: Python :: 3
Classifier: Development Status :: 3 - Alpha
Classifier: License :: OSI Approved :: MIT License
Classifier: Operating System :: OS Independent
Classifier: Intended Audience :: Developers
Classifier: Intended Audience :: Information Technology
Classifier: Intended Audience :: Science/Research
Classifier: Topic :: Scientific/Engineering
Classifier: Topic :: Database
Classifier: Topic :: Software Development :: Libraries :: Python Modules
